impkmeans/__init__.py
impkmeans/impkmeans.py
impkmeans-1.0.2.dist-info/METADATA
impkmeans-1.0.2.dist-info/WHEEL
impkmeans-1.0.2.dist-info/top_level.txt
impkmeans-1.0.2.dist-info/RECORD
