Metadata-Version: 2.4
Name: impkmeans
Version: 1.0.2
Summary: ImpKMeans: Improved K-Means initialization using KDE + KD-Tree
Home-page: https://github.com/senolali/ImpKMeans
Author: Ali Şenol
Author-email: Ali Şenol <alisenol@tarsus.edu.tr>
Project-URL: Homepage, https://github.com/senolali/ImpKMeans
Project-URL: Repository, https://github.com/senolali/ImpKMeans
Project-URL: Paper, https://doi.org/10.12700/aph.21.2.2024.2.6
Keywords: clustering,kmeans,k-means,kde,density,kd-tree,machine-learning
Requires-Python: >=3.8
Requires-Dist: numpy
Requires-Dist: scikit-learn
Dynamic: author
Dynamic: home-page
Dynamic: requires-python
